codecovopentelem/__init__.py
codecovopentelem-0.0.6.dist-info/METADATA
codecovopentelem-0.0.6.dist-info/WHEEL
codecovopentelem-0.0.6.dist-info/top_level.txt
codecovopentelem-0.0.6.dist-info/RECORD
