Metadata-Version: 2.1
Name: codecovopentelem
Version: 0.0.6
Summary: Implements Runtime Insights Support for Python Project
Home-page: https://github.com/codecov/opentelem-python
Author: Codecov
Author-email: support@codecov.io
License: UNKNOWN
Platform: UNKNOWN
Requires-Dist: coverage (>=5.5)
Requires-Dist: requests
Requires-Dist: opentelemetry-sdk
